afivmax/__init__.py
afivmax/afivmax.py
afivmax/afivmax_t.py
afivmax-0.0.1.dist-info/METADATA
afivmax-0.0.1.dist-info/WHEEL
afivmax-0.0.1.dist-info/top_level.txt
afivmax-0.0.1.dist-info/RECORD
