Metadata-Version: 2.1
Name: afivmax
Version: 0.0.1
Summary: Interview problem of Ant Fin
Home-page: https://github.com/eggachecat/afivmax
Author: sunao
Author-email: sunao_0626@hotmail.com
License: UNKNOWN
Platform: UNKNOWN
Classifier: Programming Language :: Python :: 3
